reponav/__init__.py
reponav/get_struct.py
reponav/print_contents.py
reponav/reponav.py
reponav-1.1.2.dist-info/METADATA
reponav-1.1.2.dist-info/WHEEL
reponav-1.1.2.dist-info/top_level.txt
reponav-1.1.2.dist-info/RECORD
