Metadata-Version: 2.1
Name: reponav
Version: 1.1.2
Summary: Navigating through GitHub repositories
Author: Reem Alsharabi
Author-email: <Reem.Alsharabi@outlook.com>
Keywords: python,github,repository,structure
Classifier: Development Status :: 1 - Planning
Classifier: Intended Audience :: Developers
Classifier: Programming Language :: Python :: 3
Classifier: Operating System :: Unix
Classifier: Operating System :: MacOS :: MacOS X
Classifier: Operating System :: Microsoft :: Windows
Requires-Dist: github
Requires-Dist: PyGithub
